twohundrediq/__init__.py
twohundrediq/__main__.py
twohundrediq/twohundrediq.py
twohundrediq-1.4.data/scripts/twohundrediq
twohundrediq-1.4.dist-info/METADATA
twohundrediq-1.4.dist-info/RECORD
twohundrediq-1.4.dist-info/WHEEL
twohundrediq-1.4.dist-info/top_level.txt
