Metadata-Version: 2.1
Name: twohundrediq
Version: 1.4
Summary: HQ Trivia Bot For Windows and iPhone
Home-page: https://github.com/M4cs/twohundrediq
Author: Max Bridgland
Author-email: mabridgland@protonmail.com
License: MIT
Keywords: hq trivia bot answer auto lookup ocr text recognition
Platform: UNKNOWN
Classifier: Development Status :: 5 - Production/Stable
Classifier: Environment :: Console
Classifier: Intended Audience :: Developers
Classifier: Intended Audience :: Information Technology
Classifier: Natural Language :: English
Classifier: Topic :: Software Development :: Build Tools
Classifier: License :: OSI Approved :: MIT License
Classifier: Programming Language :: Python :: 3.7
Requires-Dist: colorama (==0.3.9)
Requires-Dist: crayons (==0.1.2)
Requires-Dist: nltk (==3.3)
Requires-Dist: numpy (==1.15.1)
Requires-Dist: opencv-python (==3.4.3.18)
Requires-Dist: Pillow (==5.2.0)
Requires-Dist: psutil (==5.4.7)
Requires-Dist: pypiwin32 (==223)
Requires-Dist: pytesseract (==0.2.4)
Requires-Dist: pywin32 (==223)
Requires-Dist: pywin32-ctypes (==0.2.0)
Requires-Dist: tesseract (==0.1.3)
Requires-Dist: wikipedia (==1.4.0)
